CirclesVacanciesScrapers/__init__.py
CirclesVacanciesScrapers/database_vacancies.py
CirclesVacanciesScrapers/indeed_com_scraper.py
CirclesVacanciesScrapers/monster_com_scraper.py
recruitment_employer_local_python_package-0.0.17.dist-info/METADATA
recruitment_employer_local_python_package-0.0.17.dist-info/WHEEL
recruitment_employer_local_python_package-0.0.17.dist-info/top_level.txt
recruitment_employer_local_python_package-0.0.17.dist-info/RECORD
