Metadata-Version: 2.1
Name: recruitment-employer-local-python-package
Version: 0.0.17
Summary: PyPI Package for Circles Local recruitment scrapers Python
Home-page: https://github.com/javatechy/dokr
Author: Circles
Author-email: info@circles.life
Classifier: Programming Language :: Python :: 3
Classifier: License :: Other/Proprietary License
Classifier: Operating System :: OS Independent
